numx/__init__.py
numx/_actual_math.py
numx/_exceptions.py
numx/_numx_main.py
numx/_parser.py
numx-1.0.1.dist-info/LICENSE
numx-1.0.1.dist-info/METADATA
numx-1.0.1.dist-info/WHEEL
numx-1.0.1.dist-info/RECORD
