Metadata-Version: 2.1
Name: numx
Version: 1.0.1
Summary: Import Numbers
Home-page: https://github.com/tomhea/numx
License: BSD-2-Clause-Simplified
Keywords: math,primes,fast,cli
Author: Tom Herman
Author-email: flipjumpproject@gmail.com
Requires-Python: >=3.8,<4.0
Classifier: License :: Other/Proprietary License
Classifier: Operating System :: OS Independent
Classifier: Programming Language :: Python :: 3
Classifier: Programming Language :: Python :: 3.8
Classifier: Programming Language :: Python :: 3.9
Classifier: Programming Language :: Python :: 3.10
Classifier: Programming Language :: Python :: 3.11
Classifier: Programming Language :: Python :: 3.12
Classifier: Topic :: Scientific/Engineering :: Mathematics
Requires-Dist: sympy (==1.12)
Project-URL: Repository, https://github.com/tomhea/numx
